ddd_interface/__init__.py
ddd_interface/version.py
ddd_interface/application/__init__.py
ddd_interface/application/assembler.py
ddd_interface/domain/__init__.py
ddd_interface/domain/entity.py
ddd_interface/infrastructure/__init__.py
ddd_interface/infrastructure/converter.py
ddd_interface/objects/__init__.py
ddd_interface/objects/assembler.py
ddd_interface/objects/converter.py
ddd_interface/objects/do.py
ddd_interface/objects/dto.py
ddd_interface/objects/entity.py
ddd_interface/objects/lib.py
ddd_interface/objects/value_obj.py
ddd_interface-0.0.38.dist-info/LICENSE
ddd_interface-0.0.38.dist-info/METADATA
ddd_interface-0.0.38.dist-info/WHEEL
ddd_interface-0.0.38.dist-info/top_level.txt
ddd_interface-0.0.38.dist-info/RECORD
