Metadata-Version: 2.1
Name: ddd-interface
Version: 0.0.38
Summary: Collection of ddd objects from different packages
Author: wangziling100
Author-email: wangziling100@163.com
Classifier: Programming Language :: Python :: 3
Classifier: License :: OSI Approved :: MIT License
License-File: LICENSE
